getpaid_paynow/__init__.py
getpaid_paynow/apps.py
getpaid_paynow/forms.py
getpaid_paynow/processor.py
getpaid_paynow/urls.py
getpaid_paynow/views.py
django_getpaid_paynow-0.1.1.dist-info/LICENSE
django_getpaid_paynow-0.1.1.dist-info/WHEEL
django_getpaid_paynow-0.1.1.dist-info/METADATA
django_getpaid_paynow-0.1.1.dist-info/RECORD
